IChunqiuYuekanDiliuqiLinuxPwnLingJichuRumen/README.md
IChunqiuYuekanDiliuqiLinuxPwnLingJichuRumen/__init__.py
IChunqiuYuekanDiliuqiLinuxPwnLingJichuRumen/__main__.py
IChunqiuYuekanDiliuqiLinuxPwnLingJichuRumen/file.pdf
IChunqiuYuekanDiliuqiLinuxPwnLingJichuRumen/index.html
i_chunqiu_yuekan_diliuqi_linux_pwn_ling_jichu_rumen-2024.3.4.0.dist-info/METADATA
i_chunqiu_yuekan_diliuqi_linux_pwn_ling_jichu_rumen-2024.3.4.0.dist-info/WHEEL
i_chunqiu_yuekan_diliuqi_linux_pwn_ling_jichu_rumen-2024.3.4.0.dist-info/entry_points.txt
i_chunqiu_yuekan_diliuqi_linux_pwn_ling_jichu_rumen-2024.3.4.0.dist-info/top_level.txt
i_chunqiu_yuekan_diliuqi_linux_pwn_ling_jichu_rumen-2024.3.4.0.dist-info/RECORD
